src/__init__.py
src/__main__.py
src/server.py
takanarishimbo_datetime_mcp_server-0.3.0.dist-info/METADATA
takanarishimbo_datetime_mcp_server-0.3.0.dist-info/WHEEL
takanarishimbo_datetime_mcp_server-0.3.0.dist-info/entry_points.txt
takanarishimbo_datetime_mcp_server-0.3.0.dist-info/RECORD
