Metadata-Version: 2.4
Name: takanarishimbo-datetime-mcp-server
Version: 0.3.0
Summary: A simple MCP server that provides date and time functionality
Project-URL: Homepage, https://github.com/TakanariShimbo/uvx-datetime-mcp-server
Project-URL: Repository, https://github.com/TakanariShimbo/uvx-datetime-mcp-server.git
Project-URL: Issues, https://github.com/TakanariShimbo/uvx-datetime-mcp-server/issues
Author-email: Takanari Shimbo <takanari.shimbo@gmail.com>
License: MIT
Keywords: datetime,mcp,server,timezone
Classifier: Development Status :: 4 - Beta
Classifier: Intended Audience :: Developers
Classifier: License :: OSI Approved :: MIT License
Classifier: Programming Language :: Python :: 3
Classifier: Programming Language :: Python :: 3.10
Classifier: Programming Language :: Python :: 3.11
Classifier: Programming Language :: Python :: 3.12
Classifier: Topic :: Software Development :: Libraries
Requires-Python: >=3.10
Requires-Dist: mcp>=1.1.0
Requires-Dist: pytz>=2024.1
